[
  {
    "icon": "рџ“§",
    "title": "Gmail-test",
    "url": "https://gmail.com",
    "group": "жµ‹иЇ•1"
  },
  {
    "icon": "рџЊђ",
    "title": "жµ‹иЇ•2",
    "url": "https://www.baidu.com/",
    "group": "жµ‹иЇ•2"
  },
  {
    "icon": "рџЊђ",
    "title": "жµ‹иЇ•3",
    "url": "https://baidu.com",
    "group": "жµ‹иЇ•3"
  },
  {
    "icon": "рџЊђ",
    "title": "жµ‹иЇ•4",
    "url": "https://www.baidu.com/",
    "group": ""
  },
 {
    "icon": "рџЊђ",
    "title": "жµ‹иЇ•5",
    "url": "https://www.baidu.com/",
    "group": "12"
  }
]